JiqiZhixin2019GaofenJiaochengGithubNianduJingxuanFix1/README.md
JiqiZhixin2019GaofenJiaochengGithubNianduJingxuanFix1/__init__.py
JiqiZhixin2019GaofenJiaochengGithubNianduJingxuanFix1/__main__.py
JiqiZhixin2019GaofenJiaochengGithubNianduJingxuanFix1/file.epub
JiqiZhixin2019GaofenJiaochengGithubNianduJingxuanFix1/index.html
JiqiZhixin2019GaofenJiaochengGithubNianduJingxuanFix1/css/__init__.py
JiqiZhixin2019GaofenJiaochengGithubNianduJingxuanFix1/css/annotations.css
JiqiZhixin2019GaofenJiaochengGithubNianduJingxuanFix1/css/main.css
JiqiZhixin2019GaofenJiaochengGithubNianduJingxuanFix1/css/normalize.css
JiqiZhixin2019GaofenJiaochengGithubNianduJingxuanFix1/css/popup.css
JiqiZhixin2019GaofenJiaochengGithubNianduJingxuanFix1/font/__init__.py
JiqiZhixin2019GaofenJiaochengGithubNianduJingxuanFix1/font/fontello.eot
JiqiZhixin2019GaofenJiaochengGithubNianduJingxuanFix1/font/fontello.svg
JiqiZhixin2019GaofenJiaochengGithubNianduJingxuanFix1/font/fontello.ttf
JiqiZhixin2019GaofenJiaochengGithubNianduJingxuanFix1/font/fontello.woff
JiqiZhixin2019GaofenJiaochengGithubNianduJingxuanFix1/img/__init__.py
JiqiZhixin2019GaofenJiaochengGithubNianduJingxuanFix1/img/annotator-glyph-sprite.png
JiqiZhixin2019GaofenJiaochengGithubNianduJingxuanFix1/img/annotator-icon-sprite.png
JiqiZhixin2019GaofenJiaochengGithubNianduJingxuanFix1/img/apple-touch-icon.png
JiqiZhixin2019GaofenJiaochengGithubNianduJingxuanFix1/img/cancelfullscreen.png
JiqiZhixin2019GaofenJiaochengGithubNianduJingxuanFix1/img/close.png
JiqiZhixin2019GaofenJiaochengGithubNianduJingxuanFix1/img/fullscreen.png
JiqiZhixin2019GaofenJiaochengGithubNianduJingxuanFix1/img/loader.gif
JiqiZhixin2019GaofenJiaochengGithubNianduJingxuanFix1/img/menu-icon.png
JiqiZhixin2019GaofenJiaochengGithubNianduJingxuanFix1/img/save.png
JiqiZhixin2019GaofenJiaochengGithubNianduJingxuanFix1/img/saved.png
JiqiZhixin2019GaofenJiaochengGithubNianduJingxuanFix1/img/settings-s.png
JiqiZhixin2019GaofenJiaochengGithubNianduJingxuanFix1/img/settings.png
jiqi_zhixin_2019_gaofen_jiaocheng_github_niandu_jingxuan_fix1-2025.3.24.0.dist-info/METADATA
jiqi_zhixin_2019_gaofen_jiaocheng_github_niandu_jingxuan_fix1-2025.3.24.0.dist-info/WHEEL
jiqi_zhixin_2019_gaofen_jiaocheng_github_niandu_jingxuan_fix1-2025.3.24.0.dist-info/entry_points.txt
jiqi_zhixin_2019_gaofen_jiaocheng_github_niandu_jingxuan_fix1-2025.3.24.0.dist-info/top_level.txt
jiqi_zhixin_2019_gaofen_jiaocheng_github_niandu_jingxuan_fix1-2025.3.24.0.dist-info/RECORD
